ruishi/__init__.py
ruishi/erros.py
ruishi/main.py
ruishi/models/__init__.py
ruishi/models/request.py
ruishi/models/response.py
ruishi/models/ruishi_models.py
ruishi-0.1.9.dist-info/LICENSE
ruishi-0.1.9.dist-info/METADATA
ruishi-0.1.9.dist-info/WHEEL
ruishi-0.1.9.dist-info/top_level.txt
ruishi-0.1.9.dist-info/RECORD
