Metadata-Version: 2.1
Name: ruishi
Version: 0.1.9
Summary: 睿视接口的封装
Home-page: https://github.com/911061873/ruishi
Author: Peng1013
Author-email: qinpeng@peng1013.cn
Project-URL: Bug Tracker, https://github.com/911061873/ruishi/issues
Classifier: License :: OSI Approved :: MIT License
Classifier: Programming Language :: Python
Classifier: Programming Language :: Python :: 3
Classifier: Programming Language :: Python :: 3.10
Classifier: Programming Language :: Python :: Implementation :: CPython
Classifier: Programming Language :: Python :: Implementation :: PyPy
Requires-Python: >=3.10.0
License-File: LICENSE
Requires-Dist: httpx
Requires-Dist: pydantic
